threadref.py
threadref-1.1.5.dist-info/LICENSE
threadref-1.1.5.dist-info/METADATA
threadref-1.1.5.dist-info/WHEEL
threadref-1.1.5.dist-info/top_level.txt
threadref-1.1.5.dist-info/RECORD
