Metadata-Version: 2.1
Name: threadref
Version: 1.1.5
Summary: ``weakref`` for threads.
Home-page: https://github.com/mentalisttraceur/python-threadref
Author: Alexander Kozhevnikov
Author-email: mentalisttraceur@gmail.com
License: 0BSD
Platform: UNKNOWN
Classifier: Development Status :: 5 - Production/Stable
Classifier: Programming Language :: Python :: 3
Classifier: Programming Language :: Python :: 2
Classifier: Operating System :: OS Independent
